{
  "allfriends": [
    {
      "inr": "400",
      "paisa": 0,
      "streetaddress": "#123 test address",
      "city": "test",
      "state": "test",
      "country": "test",
      "pincode": "123456",
      "phonenumber": 9988776655,
      "email": "test@test.com",
      "firstname": "James",
      "lastname": "Bond",
      "age": 24,
      "trainerpreference": "male",
      "physiotherapist": "no",
      "packages": "400",
      "id": 4
    },
    {
      "inr": 0,
      "paisa": 0,
      "streetaddress": "#123 test address",
      "city": "test",
      "state": "test",
      "country": "test",
      "pincode": "123456",
      "phonenumber": 9988776655,
      "email": "test@test.com",
      "firstname": "Alice",
      "lastname": "Will",
      "age": 24,
      "trainerpreference": "female",
      "physiotherapist": "yes",
      "packages": "500",
      "dummy": "dummy",
      "id": 5
    },
    {
      "firstname": "testFirstName",
      "lastname": "testLastName",
      "age": 24,
      "phonenumber": 9988776655,
      "email": "test@test.com",
      "streetaddress": "#123 test address",
      "city": "test",
      "state": "test",
      "country": "test",
      "pincode": "123456",
      "trainerpreference": "male",
      "physiotherapist": "yes",
      "packages": "500",
      "inr": 10000,
      "paisa": 10,
      "id": 11
    },
    {
      "firstname": "testFirstName",
      "lastname": "testLastName",
      "age": 24,
      "phonenumber": 9988776655,
      "email": "test@test.com",
      "streetaddress": "#123 test address",
      "city": "test",
      "state": "test",
      "country": "test",
      "pincode": "123456",
      "trainerpreference": "male",
      "physiotherapist": "yes",
      "packages": "500",
      "inr": 10000,
      "paisa": 10,
      "id": 13
    },
    {
      "firstname": "testFirstName",
      "lastname": "testLastName",
      "age": 24,
      "phonenumber": 9988776655,
      "email": "test@test.com",
      "streetaddress": "#123 test address",
      "city": "test",
      "state": "test",
      "country": "test",
      "pincode": "123456",
      "trainerpreference": "male",
      "physiotherapist": "yes",
      "packages": "500",
      "inr": 10000,
      "paisa": 10,
      "id": 14
    },
    {
      "firstname": "testFirstName",
      "lastname": "testLastName",
      "age": 24,
      "phonenumber": 9988776655,
      "email": "test@test.com",
      "streetaddress": "#123 test address",
      "city": "test",
      "state": "test",
      "country": "test",
      "pincode": "123456",
      "trainerpreference": "male",
      "physiotherapist": "yes",
      "packages": "500",
      "inr": 10000,
      "paisa": 10,
      "id": 15
    },
    {
      "firstname": "testFirstName",
      "lastname": "testLastName",
      "age": 24,
      "phonenumber": 9988776655,
      "email": "test@test.com",
      "streetaddress": "#123 test address",
      "city": "test",
      "state": "test",
      "country": "test",
      "pincode": "123456",
      "trainerpreference": "male",
      "physiotherapist": "yes",
      "packages": "500",
      "inr": 10000,
      "paisa": 10,
      "id": 16
    },
    {
      "firstname": "testFirstName",
      "lastname": "testLastName",
      "age": 24,
      "phonenumber": 9988776655,
      "email": "test@test.com",
      "streetaddress": "#123 test address",
      "city": "test",
      "state": "test",
      "country": "test",
      "pincode": "123456",
      "trainerpreference": "male",
      "physiotherapist": "yes",
      "packages": "500",
      "inr": 10000,
      "paisa": 10,
      "id": 17
    },
    {
      "firstname": "testFirstName",
      "lastname": "testLastName",
      "age": 24,
      "phonenumber": 9988776655,
      "email": "test@test.com",
      "streetaddress": "#123 test address",
      "city": "test",
      "state": "test",
      "country": "test",
      "pincode": "123456",
      "trainerpreference": "male",
      "physiotherapist": "yes",
      "packages": "500",
      "inr": 10000,
      "paisa": 10,
      "id": 18
    },
    {
      "firstname": "testFirstName",
      "lastname": "testLastName",
      "age": 24,
      "phonenumber": 9988776655,
      "email": "test@test.com",
      "streetaddress": "#123 test address",
      "city": "test",
      "state": "test",
      "country": "test",
      "pincode": "123456",
      "trainerpreference": "male",
      "physiotherapist": "yes",
      "packages": "500",
      "inr": 10000,
      "paisa": 10,
      "id": 19
    },
    {
      "firstname": "testFirstName",
      "lastname": "testLastName",
      "age": 24,
      "phonenumber": 9988776655,
      "email": "test@test.com",
      "streetaddress": "#123 test address",
      "city": "test",
      "state": "test",
      "country": "test",
      "pincode": "123456",
      "trainerpreference": "male",
      "physiotherapist": "yes",
      "packages": "500",
      "inr": 10000,
      "paisa": 10,
      "id": 20
    },
    {
      "firstname": "testFirstName",
      "lastname": "testLastName",
      "age": 24,
      "phonenumber": 9988776655,
      "email": "test@test.com",
      "streetaddress": "#123 test address",
      "city": "test",
      "state": "test",
      "country": "test",
      "pincode": "123456",
      "trainerpreference": "male",
      "physiotherapist": "yes",
      "packages": "500",
      "inr": 10000,
      "paisa": 10,
      "id": 21
    },
    {
      "firstname": "testFirstName",
      "lastname": "testLastName",
      "age": 24,
      "phonenumber": 9988776655,
      "email": "test@test.com",
      "streetaddress": "#123 test address",
      "city": "test",
      "state": "test",
      "country": "test",
      "pincode": "123456",
      "trainerpreference": "male",
      "physiotherapist": "yes",
      "packages": "500",
      "inr": 10000,
      "paisa": 10,
      "id": 22
    },
    {
      "firstname": "testFirstName",
      "lastname": "testLastName",
      "age": 24,
      "phonenumber": 9988776655,
      "email": "test@test.com",
      "streetaddress": "#123 test address",
      "city": "test",
      "state": "test",
      "country": "test",
      "pincode": "123456",
      "trainerpreference": "male",
      "physiotherapist": "yes",
      "packages": "500",
      "inr": 10000,
      "paisa": 10,
      "id": 23
    },
    {
      "firstname": "testFirstName",
      "lastname": "testLastName",
      "age": 24,
      "phonenumber": 9988776655,
      "email": "test@test.com",
      "streetaddress": "#123 test address",
      "city": "test",
      "state": "test",
      "country": "test",
      "pincode": "123456",
      "trainerpreference": "male",
      "physiotherapist": "yes",
      "packages": "500",
      "inr": 10000,
      "paisa": 10,
      "id": 24
    },
    {
      "firstname": "testFirstName",
      "lastname": "testLastName",
      "age": 24,
      "phonenumber": 9988776655,
      "email": "test@test.com",
      "streetaddress": "#123 test address",
      "city": "test",
      "state": "test",
      "country": "test",
      "pincode": "123456",
      "trainerpreference": "male",
      "physiotherapist": "yes",
      "packages": "500",
      "inr": 10000,
      "paisa": 10,
      "id": 25
    },
    {
      "firstname": "testFirstName",
      "lastname": "testLastName",
      "age": 24,
      "phonenumber": 9988776655,
      "email": "test@test.com",
      "streetaddress": "#123 test address",
      "city": "test",
      "state": "test",
      "country": "test",
      "pincode": "123456",
      "trainerpreference": "male",
      "physiotherapist": "yes",
      "packages": "500",
      "inr": 10000,
      "paisa": 10,
      "id": 26
    },
    {
      "firstname": "testFirstName",
      "lastname": "testLastName",
      "age": 24,
      "phonenumber": 9988776655,
      "email": "test@test.com",
      "streetaddress": "#123 test address",
      "city": "test",
      "state": "test",
      "country": "test",
      "pincode": "123456",
      "trainerpreference": "male",
      "physiotherapist": "yes",
      "packages": "500",
      "inr": 10000,
      "paisa": 10,
      "id": 27
    },
    {
      "firstname": "testFirstName",
      "lastname": "testLastName",
      "age": 24,
      "phonenumber": 9988776655,
      "email": "test@test.com",
      "streetaddress": "#123 test address",
      "city": "test",
      "state": "test",
      "country": "test",
      "pincode": "123456",
      "trainerpreference": "male",
      "physiotherapist": "yes",
      "packages": "500",
      "inr": 10000,
      "paisa": 10,
      "id": 28
    },
    {
      "firstname": "testFirstName",
      "lastname": "testLastName",
      "age": 24,
      "phonenumber": 9988776655,
      "email": "test@test.com",
      "streetaddress": "#123 test address",
      "city": "test",
      "state": "test",
      "country": "test",
      "pincode": "123456",
      "trainerpreference": "male",
      "physiotherapist": "yes",
      "packages": "500",
      "inr": 10000,
      "paisa": 10,
      "id": 29
    },
    {
      "firstname": "testFirstName",
      "lastname": "testLastName",
      "age": 24,
      "phonenumber": 9988776655,
      "email": "test@test.com",
      "streetaddress": "#123 test address",
      "city": "test",
      "state": "test",
      "country": "test",
      "pincode": "123456",
      "trainerpreference": "male",
      "physiotherapist": "yes",
      "packages": "500",
      "inr": 10000,
      "paisa": 10,
      "id": 30
    },
    {
      "firstname": "testFirstName",
      "lastname": "testLastName",
      "age": 24,
      "phonenumber": 9988776655,
      "email": "test@test.com",
      "streetaddress": "#123 test address",
      "city": "test",
      "state": "test",
      "country": "test",
      "pincode": "123456",
      "trainerpreference": "male",
      "physiotherapist": "yes",
      "packages": "500",
      "inr": 10000,
      "paisa": 10,
      "id": 31
    },
    {
      "firstname": "testFirstName",
      "lastname": "testLastName",
      "age": 24,
      "phonenumber": 9988776655,
      "email": "test@test.com",
      "streetaddress": "#123 test address",
      "city": "test",
      "state": "test",
      "country": "test",
      "pincode": "123456",
      "trainerpreference": "male",
      "physiotherapist": "yes",
      "packages": "500",
      "inr": 10000,
      "paisa": 10,
      "id": 32
    },
    {
      "firstname": "testFirstName",
      "lastname": "testLastName",
      "age": 24,
      "phonenumber": 9988776655,
      "email": "test@test.com",
      "streetaddress": "#123 test address",
      "city": "test",
      "state": "test",
      "country": "test",
      "pincode": "123456",
      "trainerpreference": "male",
      "physiotherapist": "yes",
      "packages": "500",
      "inr": 10000,
      "paisa": 10,
      "id": 33
    },
    {
      "firstname": "testFirstName",
      "lastname": "testLastName",
      "age": 24,
      "phonenumber": 9988776655,
      "email": "test@test.com",
      "streetaddress": "#123 test address",
      "city": "test",
      "state": "test",
      "country": "test",
      "pincode": "123456",
      "trainerpreference": "male",
      "physiotherapist": "yes",
      "packages": "500",
      "inr": 10000,
      "paisa": 10,
      "id": 34
    },
    {
      "firstname": "testFirstName",
      "lastname": "testLastName",
      "age": 24,
      "phonenumber": 9988776655,
      "email": "test@test.com",
      "streetaddress": "#123 test address",
      "city": "test",
      "state": "test",
      "country": "test",
      "pincode": "123456",
      "trainerpreference": "male",
      "physiotherapist": "yes",
      "packages": "500",
      "inr": 10000,
      "paisa": 10,
      "id": 35
    },
    {
      "firstname": "testFirstName",
      "lastname": "testLastName",
      "age": 24,
      "phonenumber": 9988776655,
      "email": "test@test.com",
      "streetaddress": "#123 test address",
      "city": "test",
      "state": "test",
      "country": "test",
      "pincode": "123456",
      "trainerpreference": "male",
      "physiotherapist": "yes",
      "packages": "500",
      "inr": 10000,
      "paisa": 10,
      "id": 36
    },
    {
      "firstname": "testFirstName",
      "lastname": "testLastName",
      "age": 24,
      "phonenumber": 9988776655,
      "email": "test@test.com",
      "streetaddress": "#123 test address",
      "city": "test",
      "state": "test",
      "country": "test",
      "pincode": "123456",
      "trainerpreference": "male",
      "physiotherapist": "yes",
      "packages": "500",
      "inr": 10000,
      "paisa": 10,
      "id": 37
    },
    {
      "firstname": "testFirstName",
      "lastname": "testLastName",
      "age": 24,
      "phonenumber": 9988776655,
      "email": "test@test.com",
      "streetaddress": "#123 test address",
      "city": "test",
      "state": "test",
      "country": "test",
      "pincode": "123456",
      "trainerpreference": "male",
      "physiotherapist": "yes",
      "packages": "500",
      "inr": 10000,
      "paisa": 10,
      "id": 38
    },
    {
      "firstname": "testFirstName",
      "lastname": "testLastName",
      "age": 24,
      "phonenumber": 9988776655,
      "email": "test@test.com",
      "streetaddress": "#123 test address",
      "city": "test",
      "state": "test",
      "country": "test",
      "pincode": "123456",
      "trainerpreference": "male",
      "physiotherapist": "yes",
      "packages": "500",
      "inr": 10000,
      "paisa": 10,
      "id": 39
    },
    {
      "firstname": "testFirstName",
      "lastname": "testLastName",
      "age": 24,
      "phonenumber": 9988776655,
      "email": "test@test.com",
      "streetaddress": "#123 test address",
      "city": "test",
      "state": "test",
      "country": "test",
      "pincode": "123456",
      "trainerpreference": "male",
      "physiotherapist": "yes",
      "packages": "500",
      "inr": 10000,
      "paisa": 10,
      "id": 40
    },
    {
      "firstname": "testFirstName",
      "lastname": "testLastName",
      "age": 24,
      "phonenumber": 9988776655,
      "email": "test@test.com",
      "streetaddress": "#123 test address",
      "city": "test",
      "state": "test",
      "country": "test",
      "pincode": "123456",
      "trainerpreference": "male",
      "physiotherapist": "yes",
      "packages": "500",
      "inr": 10000,
      "paisa": 10,
      "id": 41
    },
    {
      "firstname": "testFirstName",
      "lastname": "testLastName",
      "age": 24,
      "phonenumber": 9988776655,
      "email": "test@test.com",
      "streetaddress": "#123 test address",
      "city": "test",
      "state": "test",
      "country": "test",
      "pincode": "123456",
      "trainerpreference": "male",
      "physiotherapist": "yes",
      "packages": "500",
      "inr": 10000,
      "paisa": 10,
      "id": 42
    },
    {
      "firstname": "testFirstName",
      "lastname": "testLastName",
      "age": 24,
      "phonenumber": 9988776655,
      "email": "test@test.com",
      "streetaddress": "#123 test address",
      "city": "test",
      "state": "test",
      "country": "test",
      "pincode": "123456",
      "trainerpreference": "male",
      "physiotherapist": "yes",
      "packages": "500",
      "inr": 10000,
      "paisa": 10,
      "id": 43
    },
    {
      "firstname": "testFirstName",
      "lastname": "testLastName",
      "age": 24,
      "phonenumber": 9988776655,
      "email": "test@test.com",
      "streetaddress": "#123 test address",
      "city": "test",
      "state": "test",
      "country": "test",
      "pincode": "123456",
      "trainerpreference": "male",
      "physiotherapist": "yes",
      "packages": "500",
      "inr": 10000,
      "paisa": 10,
      "id": 45
    },
    {
      "firstname": "testFirstName",
      "lastname": "testLastName",
      "age": 24,
      "phonenumber": 9988776655,
      "email": "test@test.com",
      "streetaddress": "#123 test address",
      "city": "test",
      "state": "test",
      "country": "test",
      "pincode": "123456",
      "trainerpreference": "male",
      "physiotherapist": "yes",
      "packages": "500",
      "inr": 10000,
      "paisa": 10,
      "id": 46
    },
    {
      "firstname": "testFirstName",
      "lastname": "testLastName",
      "age": 24,
      "phonenumber": 9988776655,
      "email": "test@test.com",
      "streetaddress": "#123 test address",
      "city": "test",
      "state": "test",
      "country": "test",
      "pincode": "123456",
      "trainerpreference": "male",
      "physiotherapist": "yes",
      "packages": "500",
      "inr": 10000,
      "paisa": 10,
      "id": 47
    },
    {
      "firstname": "testFirstName",
      "lastname": "testLastName",
      "age": 24,
      "phonenumber": 9988776655,
      "email": "test@test.com",
      "streetaddress": "#123 test address",
      "city": "test",
      "state": "test",
      "country": "test",
      "pincode": "123456",
      "trainerpreference": "male",
      "physiotherapist": "yes",
      "packages": "500",
      "inr": 10000,
      "paisa": 10,
      "id": 48
    },
    {
      "firstname": "testFirstName",
      "lastname": "testLastName",
      "age": 24,
      "phonenumber": 9988776655,
      "email": "test@test.com",
      "streetaddress": "#123 test address",
      "city": "test",
      "state": "test",
      "country": "test",
      "pincode": "123456",
      "trainerpreference": "male",
      "physiotherapist": "yes",
      "packages": "500",
      "inr": 10000,
      "paisa": 10,
      "id": 49
    },
    {
      "firstname": "testFirstName",
      "lastname": "testLastName",
      "age": 24,
      "phonenumber": 9988776655,
      "email": "test@test.com",
      "streetaddress": "#123 test address",
      "city": "test",
      "state": "test",
      "country": "test",
      "pincode": "123456",
      "trainerpreference": "male",
      "physiotherapist": "yes",
      "packages": "500",
      "inr": 10000,
      "paisa": 10,
      "id": 50
    },
    {
      "firstname": "testFirstName",
      "lastname": "testLastName",
      "age": 24,
      "phonenumber": 9988776655,
      "email": "test@test.com",
      "streetaddress": "#123 test address",
      "city": "test",
      "state": "test",
      "country": "test",
      "pincode": "123456",
      "trainerpreference": "male",
      "physiotherapist": "yes",
      "packages": "500",
      "inr": 10000,
      "paisa": 10,
      "id": 51
    },
    {
      "firstname": "testFirstName",
      "lastname": "testLastName",
      "age": 24,
      "phonenumber": 9988776655,
      "email": "test@test.com",
      "streetaddress": "#123 test address",
      "city": "test",
      "state": "test",
      "country": "test",
      "pincode": "123456",
      "trainerpreference": "male",
      "physiotherapist": "yes",
      "packages": "500",
      "inr": 10000,
      "paisa": 10,
      "id": 52
    },
    {
      "firstname": "testFirstName",
      "lastname": "testLastName",
      "age": 24,
      "phonenumber": 9988776655,
      "email": "test@test.com",
      "streetaddress": "#123 test address",
      "city": "test",
      "state": "test",
      "country": "test",
      "pincode": "123456",
      "trainerpreference": "male",
      "physiotherapist": "yes",
      "packages": "500",
      "inr": 10000,
      "paisa": 10,
      "id": 53
    },
    {
      "firstname": "testFirstName",
      "lastname": "testLastName",
      "age": 24,
      "phonenumber": 9988776655,
      "email": "test@test.com",
      "streetaddress": "#123 test address",
      "city": "test",
      "state": "test",
      "country": "test",
      "pincode": "123456",
      "trainerpreference": "male",
      "physiotherapist": "yes",
      "packages": "500",
      "inr": 10000,
      "paisa": 10,
      "id": 54
    },
    {
      "firstname": "testFirstName",
      "lastname": "testLastName",
      "age": 24,
      "phonenumber": 9988776655,
      "email": "test@test.com",
      "streetaddress": "#123 test address",
      "city": "test",
      "state": "test",
      "country": "test",
      "pincode": "123456",
      "trainerpreference": "male",
      "physiotherapist": "yes",
      "packages": "500",
      "inr": 10000,
      "paisa": 10,
      "id": 55
    },
    {
      "firstname": "testFirstName",
      "lastname": "testLastName",
      "age": 24,
      "phonenumber": 9988776655,
      "email": "test@test.com",
      "streetaddress": "#123 test address",
      "city": "test",
      "state": "test",
      "country": "test",
      "pincode": "123456",
      "trainerpreference": "male",
      "physiotherapist": "yes",
      "packages": "500",
      "inr": 10000,
      "paisa": 10,
      "id": 58
    },
    {
      "firstname": "testFirstName",
      "lastname": "testLastName",
      "age": 24,
      "phonenumber": 9988776655,
      "email": "test@test.com",
      "streetaddress": "#123 test address",
      "city": "test",
      "state": "test",
      "country": "test",
      "pincode": "123456",
      "trainerpreference": "male",
      "physiotherapist": "yes",
      "packages": "500",
      "inr": 10000,
      "paisa": 10,
      "id": 59
    },
    {
      "firstname": "testFirstName",
      "lastname": "testLastName",
      "age": 24,
      "phonenumber": 9988776655,
      "email": "test@test.com",
      "streetaddress": "#123 test address",
      "city": "test",
      "state": "test",
      "country": "test",
      "pincode": "123456",
      "trainerpreference": "male",
      "physiotherapist": "yes",
      "packages": "500",
      "inr": 10000,
      "paisa": 10,
      "id": 61
    },
    {
      "firstname": "testFirstName",
      "lastname": "testLastName",
      "age": 24,
      "phonenumber": 9988776655,
      "email": "test@test.com",
      "streetaddress": "#123 test address",
      "city": "test",
      "state": "test",
      "country": "test",
      "pincode": "123456",
      "trainerpreference": "male",
      "physiotherapist": "yes",
      "packages": "500",
      "inr": 10000,
      "paisa": 10,
      "id": 62
    },
    {
      "firstname": "testFirstName",
      "lastname": "testLastName",
      "age": 24,
      "phonenumber": 9988776655,
      "email": "test@test.com",
      "streetaddress": "#123 test address",
      "city": "test",
      "state": "test",
      "country": "test",
      "pincode": "123456",
      "trainerpreference": "male",
      "physiotherapist": "yes",
      "packages": "500",
      "inr": 10000,
      "paisa": 10,
      "id": 63
    },
    {
      "firstname": "testFirstName",
      "lastname": "testLastName",
      "age": 24,
      "phonenumber": 9988776655,
      "email": "test@test.com",
      "streetaddress": "#123 test address",
      "city": "test",
      "state": "test",
      "country": "test",
      "pincode": "123456",
      "trainerpreference": "male",
      "physiotherapist": "yes",
      "packages": "500",
      "inr": 10000,
      "paisa": 10,
      "id": 64
    },
    {
      "inr": "1000",
      "paisa": 0,
      "streetaddress": "#123 test address",
      "city": "test",
      "state": "test",
      "country": "test",
      "pincode": "123456",
      "phonenumber": 9988776655,
      "email": "test@test.com",
      "firstname": "testFirstName",
      "lastname": "testLastName",
      "age": 24,
      "trainerpreference": "male",
      "physiotherapist": "yes",
      "packages": "1000",
      "id": 65
    },
    {
      "firstname": "testFirstName",
      "lastname": "testLastName",
      "age": 24,
      "phonenumber": 9988776655,
      "email": "test@test.com",
      "streetaddress": "#123 test address",
      "city": "test",
      "state": "test",
      "country": "test",
      "pincode": "123456",
      "trainerpreference": "male",
      "physiotherapist": "yes",
      "packages": "500",
      "inr": 10000,
      "paisa": 10,
      "id": 66
    },
    {
      "firstname": "testFirstName",
      "lastname": "testLastName",
      "age": 24,
      "phonenumber": 9988776655,
      "email": "test@test.com",
      "streetaddress": "#123 test address",
      "city": "test",
      "state": "test",
      "country": "test",
      "pincode": "123456",
      "trainerpreference": "male",
      "physiotherapist": "yes",
      "packages": "500",
      "inr": 10000,
      "paisa": 10,
      "id": 67
    },
    {
      "firstname": "testFirstName",
      "lastname": "testLastName",
      "age": 24,
      "phonenumber": 9988776655,
      "email": "test@test.com",
      "streetaddress": "#123 test address",
      "city": "test",
      "state": "test",
      "country": "test",
      "pincode": "123456",
      "trainerpreference": "male",
      "physiotherapist": "yes",
      "packages": "500",
      "inr": 10000,
      "paisa": 10,
      "id": 68
    },
    {
      "firstname": "testFirstName",
      "lastname": "testLastName",
      "age": 24,
      "phonenumber": 9988776655,
      "email": "test@test.com",
      "streetaddress": "#123 test address",
      "city": "test",
      "state": "test",
      "country": "test",
      "pincode": "123456",
      "trainerpreference": "male",
      "physiotherapist": "yes",
      "packages": "500",
      "inr": 10000,
      "paisa": 10,
      "id": 69
    },
    {
      "firstname": "testFirstName",
      "lastname": "testLastName",
      "age": 24,
      "phonenumber": 9988776655,
      "email": "test@test.com",
      "streetaddress": "#123 test address",
      "city": "test",
      "state": "test",
      "country": "test",
      "pincode": "123456",
      "trainerpreference": "male",
      "physiotherapist": "yes",
      "packages": "500",
      "inr": 10000,
      "paisa": 10,
      "id": 70
    },
    {
      "firstname": "testFirstName",
      "lastname": "testLastName",
      "age": 24,
      "phonenumber": 9988776655,
      "email": "test@test.com",
      "streetaddress": "#123 test address",
      "city": "test",
      "state": "test",
      "country": "test",
      "pincode": "123456",
      "trainerpreference": "male",
      "physiotherapist": "yes",
      "packages": "500",
      "inr": 10000,
      "paisa": 10,
      "id": 71
    },
    {
      "firstname": "testFirstName",
      "lastname": "testLastName",
      "age": 24,
      "phonenumber": 9988776655,
      "email": "test@test.com",
      "streetaddress": "#123 test address",
      "city": "test",
      "state": "test",
      "country": "test",
      "pincode": "123456",
      "trainerpreference": "male",
      "physiotherapist": "yes",
      "packages": "500",
      "inr": 10000,
      "paisa": 10,
      "id": 72
    },
    {
      "inr": "2000",
      "paisa": 0,
      "streetaddress": "#123 test address",
      "city": "test",
      "state": "test",
      "country": "test",
      "pincode": "123456",
      "phonenumber": 9988776655,
      "email": "test@test.com",
      "firstname": "testFirstName",
      "lastname": "testLastName",
      "age": 24,
      "trainerpreference": "male",
      "physiotherapist": "yes",
      "packages": "2000",
      "id": 73
    },
    {
      "firstname": "testFirstName",
      "lastname": "testLastName",
      "age": 24,
      "phonenumber": 9988776655,
      "email": "test@test.com",
      "streetaddress": "#123 test address",
      "city": "test",
      "state": "test",
      "country": "test",
      "pincode": "123456",
      "trainerpreference": "male",
      "physiotherapist": "yes",
      "packages": "500",
      "inr": 10000,
      "paisa": 10,
      "id": 74
    },
    {
      "firstname": "testFirstName",
      "lastname": "testLastName",
      "age": 24,
      "phonenumber": 9988776655,
      "email": "test@test.com",
      "streetaddress": "#123 test address",
      "city": "test",
      "state": "test",
      "country": "test",
      "pincode": "123456",
      "trainerpreference": "male",
      "physiotherapist": "yes",
      "packages": "500",
      "inr": 10000,
      "paisa": 10,
      "id": 75
    },
    {
      "firstname": "testFirstName",
      "lastname": "testLastName",
      "age": 24,
      "phonenumber": 9988776655,
      "email": "test@test.com",
      "streetaddress": "#123 test address",
      "city": "test",
      "state": "test",
      "country": "test",
      "pincode": "123456",
      "trainerpreference": "male",
      "physiotherapist": "yes",
      "packages": "500",
      "inr": 10000,
      "paisa": 10,
      "id": 77
    },
    {
      "inr": 500,
      "paisa": 0,
      "streetaddress": "#123 test address",
      "city": "test",
      "state": "test",
      "country": "test",
      "pincode": "123456",
      "phonenumber": 9988776655,
      "email": "test@test.com",
      "firstname": "Anna",
      "lastname": "Barnes",
      "age": 25,
      "trainerpreference": "male",
      "physiotherapist": "yes",
      "packages": "Onetime",
      "id": 78
    },
    {
      "firstname": "testFirstName",
      "lastname": "testLastName",
      "age": 24,
      "phonenumber": 9988776655,
      "email": "test@test.com",
      "streetaddress": "#123 test address",
      "city": "test",
      "state": "test",
      "country": "test",
      "pincode": "123456",
      "trainerpreference": "male",
      "physiotherapist": "yes",
      "packages": "500",
      "inr": 10000,
      "paisa": 10,
      "id": 79
    },
    {
      "firstname": "testFirstName",
      "lastname": "testLastName",
      "age": 24,
      "phonenumber": 9988776655,
      "email": "test@test.com",
      "streetaddress": "#123 test address",
      "city": "test",
      "state": "test",
      "country": "test",
      "pincode": "123456",
      "trainerpreference": "male",
      "physiotherapist": "yes",
      "packages": "500",
      "inr": 10000,
      "paisa": 10,
      "id": 80
    },
    {
      "firstname": "testFirstName",
      "lastname": "testLastName",
      "age": 24,
      "phonenumber": 9988776655,
      "email": "test@test.com",
      "streetaddress": "#123 test address",
      "city": "test",
      "state": "test",
      "country": "test",
      "pincode": "123456",
      "trainerpreference": "male",
      "physiotherapist": "yes",
      "packages": "500",
      "inr": 10000,
      "paisa": 10,
      "id": 81
    },
    {
      "firstname": "testFirstName",
      "lastname": "testLastName",
      "age": 24,
      "phonenumber": 9988776655,
      "email": "test@test.com",
      "streetaddress": "#123 test address",
      "city": "test",
      "state": "test",
      "country": "test",
      "pincode": "123456",
      "trainerpreference": "male",
      "physiotherapist": "yes",
      "packages": "500",
      "inr": 10000,
      "paisa": 10,
      "id": 82
    },
    {
      "firstname": "testFirstName",
      "lastname": "testLastName",
      "age": 24,
      "phonenumber": 9988776655,
      "email": "test@test.com",
      "streetaddress": "#123 test address",
      "city": "test",
      "state": "test",
      "country": "test",
      "pincode": "123456",
      "trainerpreference": "male",
      "physiotherapist": "yes",
      "packages": "500",
      "inr": 10000,
      "paisa": 10,
      "id": 83
    },
    {
      "firstname": "testFirstName",
      "lastname": "testLastName",
      "age": 24,
      "phonenumber": 9988776655,
      "email": "test@test.com",
      "streetaddress": "#123 test address",
      "city": "test",
      "state": "test",
      "country": "test",
      "pincode": "123456",
      "trainerpreference": "male",
      "physiotherapist": "yes",
      "packages": "500",
      "inr": 10000,
      "paisa": 10,
      "id": 84
    },
    {
      "firstname": "testFirstName",
      "lastname": "testLastName",
      "age": 24,
      "phonenumber": 9988776655,
      "email": "test@test.com",
      "streetaddress": "#123 test address",
      "city": "test",
      "state": "test",
      "country": "test",
      "pincode": "123456",
      "trainerpreference": "male",
      "physiotherapist": "yes",
      "packages": "500",
      "inr": 10000,
      "paisa": 10,
      "id": 86
    },
    {
      "firstname": "testFirstName",
      "lastname": "testLastName",
      "age": 24,
      "phonenumber": 9988776655,
      "email": "test@test.com",
      "streetaddress": "#123 test address",
      "city": "test",
      "state": "test",
      "country": "test",
      "pincode": "123456",
      "trainerpreference": "male",
      "physiotherapist": "yes",
      "packages": "500",
      "inr": 10000,
      "paisa": 10,
      "id": 88
    },
    {
      "firstname": "testFirstName",
      "lastname": "testLastName",
      "age": 24,
      "phonenumber": 9988776655,
      "email": "test@test.com",
      "streetaddress": "#123 test address",
      "city": "test",
      "state": "test",
      "country": "test",
      "pincode": "123456",
      "trainerpreference": "male",
      "physiotherapist": "yes",
      "packages": "500",
      "inr": 10000,
      "paisa": 10,
      "id": 89
    },
    {
      "firstname": "Alex",
      "lastname": "Jones",
      "phonenumber": 8888888888,
      "email": "aj@d.com",
      "message": "OKAY",
      "id": 96
    },
    {
      "firstname": "Fin",
      "lastname": "King",
      "phonenumber": 7777777777,
      "email": "F@k.com",
      "message": "Good",
      "id": 97
    },
    {
      "firstname": "Raj",
      "lastname": "Kumar",
      "phonenumber": 6666666666,
      "email": "raj@g.com",
      "message": "Pls call me",
      "id": 98
    },
    {
      "firstname": "Rahul",
      "lastname": "Joshi",
      "phonenumber": 8888888888,
      "email": "rj@a.com",
      "message": "Hello",
      "id": 100
    },
    {
      "inr": "2000",
      "paisa": 0,
      "streetaddress": "A/17, Mall rd",
      "city": "Pune",
      "state": "Maharashtra",
      "country": "India",
      "pincode": "400095",
      "phonenumber": "9999999999",
      "email": "rm@g.com",
      "firstname": "Ramesh",
      "lastname": "Dev",
      "age": 45,
      "trainerpreference": "nopreference",
      "physiotherapist": "no",
      "packages": "2000",
      "id": 101
    },
    {
      "inr": "400",
      "paisa": 0,
      "streetaddress": "B/23, Mall rd",
      "city": "Delhi",
      "state": "Delhi",
      "country": "India",
      "pincode": "888888",
      "phonenumber": "6666666666",
      "email": "as@d.com",
      "firstname": "Saket",
      "lastname": "Shah",
      "age": 47,
      "trainerpreference": "male",
      "physiotherapist": "yes",
      "packages": "400",
      "id": 102
    },
    {
      "firstname": "testname",
      "lastname": "test",
      "phonenumber": 9988776655,
      "email": "test@test.com",
      "message": "test message",
      "id": 103
    },
    {
      "firstname": "testname",
      "lastname": "test",
      "phonenumber": 9988776655,
      "email": "test@test.com",
      "message": "test message",
      "id": 104
    },
    {
      "firstname": "testname",
      "lastname": "test",
      "phonenumber": 9988776655,
      "email": "test@test.com",
      "message": "test message",
      "id": 105
    },
    {
      "firstname": "testname",
      "lastname": "test",
      "phonenumber": 9988776655,
      "email": "test@test.com",
      "message": "test message",
      "id": 106
    },
    {
      "firstname": "Sam",
      "lastname": "Wilson",
      "phonenumber": 77777777,
      "email": "sm@g.com",
      "message": "Bye",
      "id": 107
    },
    {
      "firstname": "testname",
      "lastname": "test",
      "phonenumber": 9988776655,
      "email": "test@test.com",
      "message": "test message",
      "id": 108
    },
    {
      "firstname": "testname",
      "lastname": "test",
      "phonenumber": 9988776655,
      "email": "test@test.com",
      "message": "test message",
      "id": 109
    },
    {
      "firstname": "Sam",
      "lastname": "Dev",
      "phonenumber": 9999999999,
      "email": "rm@g.com",
      "message": "ok",
      "id": 110
    },
    {
      "firstname": "testname",
      "lastname": "test",
      "phonenumber": 9988776655,
      "email": "test@test.com",
      "message": "test message",
      "id": 111
    },
    {
      "firstname": "testname",
      "lastname": "test",
      "phonenumber": 9988776655,
      "email": "test@test.com",
      "message": "test message",
      "id": 112
    },
    {
      "firstname": "testname",
      "lastname": "test",
      "phonenumber": 9988776655,
      "email": "test@test.com",
      "message": "test message",
      "id": 113
    },
    {
      "firstname": "testname",
      "lastname": "test",
      "phonenumber": 9988776655,
      "email": "test@test.com",
      "message": "test message",
      "id": 114
    },
    {
      "firstname": "testname",
      "lastname": "test",
      "phonenumber": 9988776655,
      "email": "test@test.com",
      "message": "test message",
      "id": 115
    },
    {
      "firstname": "testname",
      "lastname": "test",
      "phonenumber": 9988776655,
      "email": "test@test.com",
      "message": "test message",
      "id": 116
    },
    {
      "firstname": "testname",
      "lastname": "test",
      "phonenumber": 9988776655,
      "email": "test@test.com",
      "message": "test message",
      "id": 117
    },
    {
      "firstname": "testname",
      "lastname": "test",
      "phonenumber": 9988776655,
      "email": "test@test.com",
      "message": "test message",
      "id": 118
    },
    {
      "firstname": "testname",
      "lastname": "test",
      "phonenumber": 9988776655,
      "email": "test@test.com",
      "message": "test message",
      "id": 119
    },
    {
      "firstname": "testname",
      "lastname": "test",
      "phonenumber": 9988776655,
      "email": "test@test.com",
      "message": "test message",
      "id": 120
    },
    {
      "firstname": "testname",
      "lastname": "test",
      "phonenumber": 9988776655,
      "email": "test@test.com",
      "message": "test message",
      "id": 121
    },
    {
      "firstname": "testname",
      "lastname": "test",
      "phonenumber": 9988776655,
      "email": "test@test.com",
      "message": "test message",
      "id": 122
    },
    {
      "firstname": "testname",
      "lastname": "test",
      "phonenumber": 9988776655,
      "email": "test@test.com",
      "message": "test message",
      "id": 124
    },
    {
      "firstname": "testname",
      "lastname": "test",
      "phonenumber": 9988776655,
      "email": "test@test.com",
      "message": "test message",
      "id": 125
    },
    {
      "firstname": "testname",
      "lastname": "test",
      "phonenumber": 9988776655,
      "email": "test@test.com",
      "message": "test message",
      "id": 126
    },
    {
      "firstname": "testname",
      "lastname": "test",
      "phonenumber": 9988776655,
      "email": "test@test.com",
      "message": "test message",
      "id": 127
    },
    {
      "firstname": "testname",
      "lastname": "test",
      "phonenumber": 9988776655,
      "email": "test@test.com",
      "message": "test message",
      "id": 128
    },
    {
      "firstname": "testname",
      "lastname": "test",
      "phonenumber": 9988776655,
      "email": "test@test.com",
      "message": "test message",
      "id": 129
    },
    {
      "firstname": "testname",
      "lastname": "test",
      "phonenumber": 9988776655,
      "email": "test@test.com",
      "message": "test message",
      "id": 130
    },
    {
      "inr": "3000",
      "paisa": 0,
      "streetaddress": "A/6, Town rd",
      "city": "Mumbai",
      "state": "Maharashtra",
      "country": "India",
      "pincode": "400095",
      "phonenumber": "88888888",
      "email": "mj@g.com",
      "firstname": "Amit",
      "lastname": "Singh",
      "age": 41,
      "trainerpreference": "male",
      "physiotherapist": "yes",
      "packages": "3000",
      "id": 131
    },
    {
      "firstname": "testname",
      "lastname": "test",
      "phonenumber": 9988776655,
      "email": "test@test.com",
      "message": "test message",
      "id": 132
    },
    {
      "inr": "2000",
      "paisa": 0,
      "streetaddress": "A/2",
      "city": "Delhi",
      "state": "Delhi",
      "country": "India",
      "pincode": "666666",
      "phonenumber": "88888888",
      "email": "sk@g.com",
      "firstname": "Shashi",
      "lastname": "Gupta",
      "age": 45,
      "trainerpreference": "male",
      "physiotherapist": "yes",
      "packages": "2000",
      "id": 133
    },
    {
      "inr": "2000",
      "paisa": 0,
      "streetaddress": "A/6, Town rd",
      "city": "Mumbai",
      "state": "Maharashtra",
      "country": "India",
      "pincode": "400095",
      "phonenumber": "88888888",
      "email": "mj@g.com",
      "firstname": "Mahesh",
      "lastname": "Singh",
      "age": 38,
      "trainerpreference": "male",
      "physiotherapist": "yes",
      "packages": "2000",
      "id": 134
    },
    {
      "inr": "2000",
      "paisa": 0,
      "streetaddress": "A/17, Mall rd",
      "city": "Pune",
      "state": "Maharashtra",
      "country": "India",
      "pincode": "400095",
      "phonenumber": "09999999999",
      "email": "rm@g.com",
      "firstname": "Ramesh",
      "lastname": "Mehta",
      "age": 51,
      "trainerpreference": "male",
      "physiotherapist": "yes",
      "packages": "2000",
      "id": 135
    },
    {
      "firstname": "Ramesh",
      "lastname": "Dev",
      "phonenumber": 9999999999,
      "email": "rm@g.com",
      "message": "Good work",
      "id": 136
    },
    {
      "firstname": "testname",
      "lastname": "test",
      "phonenumber": 9988776655,
      "email": "test@test.com",
      "message": "test message",
      "id": 137
    },
    {
      "inr": "2000",
      "paisa": 0,
      "streetaddress": "A/17, Mall rd",
      "city": "Pune",
      "state": "Maharashtra",
      "country": "India",
      "pincode": "400095",
      "phonenumber": "19999999999",
      "email": "rm@g.com",
      "firstname": "Ramesh",
      "lastname": "Kumar",
      "age": 56,
      "trainerpreference": "male",
      "physiotherapist": "yes",
      "packages": "2000",
      "id": 138
    },
    {
      "firstname": "Zack",
      "lastname": "Brown",
      "phonenumber": 88888888,
      "email": "mj@g.com",
      "message": "Need help",
      "id": 139
    },
    {
      "inr": "3000",
      "paisa": 0,
      "streetaddress": "A/17, Mall rd",
      "city": "Pune",
      "state": "Maharashtra",
      "country": "India",
      "pincode": "400095",
      "phonenumber": "09999999999",
      "email": "rm@g.com",
      "firstname": "Rajeev",
      "lastname": "Dev",
      "age": 19,
      "trainerpreference": "male",
      "physiotherapist": "yes",
      "packages": "3000",
      "id": 140
    },
    {
      "inr": "2000",
      "paisa": 0,
      "streetaddress": "A/17, Mall rd",
      "city": "Pune",
      "state": "Maharashtra",
      "country": "India",
      "pincode": "400095",
      "phonenumber": "09999999999",
      "email": "rm@g.com",
      "firstname": "Rishi",
      "lastname": "Dev",
      "age": 53,
      "trainerpreference": "male",
      "physiotherapist": "yes",
      "packages": "2000",
      "id": 141
    },
    {
      "firstname": "testname",
      "lastname": "test",
      "phonenumber": 9988776655,
      "email": "test@test.com",
      "message": "test message",
      "id": 142
    },
    {
      "inr": "3000",
      "paisa": 0,
      "streetaddress": "A/2",
      "city": "Delhi",
      "state": "Delhi",
      "country": "India",
      "pincode": "666666",
      "phonenumber": "88888888",
      "email": "sk@g.com",
      "firstname": "Kiran",
      "lastname": "Gupta",
      "age": 48,
      "trainerpreference": "male",
      "physiotherapist": "yes",
      "packages": "3000",
      "id": 143
    },
    {
      "firstname": "testname",
      "lastname": "test",
      "phonenumber": 9988776655,
      "email": "test@test.com",
      "message": "test message",
      "id": 144
    },
    {
      "firstname": "testname",
      "lastname": "test",
      "phonenumber": 9988776655,
      "email": "test@test.com",
      "message": "test message",
      "id": 145
    }
  ]
}